safe_builtins/__about__.py
safe_builtins/__init__.py
safe_builtins/main.py
safe_builtins/py.typed
safe_builtins-0.1.0.dist-info/METADATA
safe_builtins-0.1.0.dist-info/WHEEL
safe_builtins-0.1.0.dist-info/licenses/LICENSE
safe_builtins-0.1.0.dist-info/RECORD
