Metadata-Version: 2.4
Name: safe-builtins
Version: 0.1.0
Summary: Python builtins wrapped with rust-like Result
Author-email: Kamal Fasya <kamalfasya01@gmail.com>
License: MIT License
License-File: LICENSE
Keywords: builtins,safe,utils
Classifier: License :: OSI Approved :: MIT License
Classifier: Programming Language :: Python :: 3
Classifier: Programming Language :: Python :: 3 :: Only
Classifier: Programming Language :: Python :: 3.10
Classifier: Programming Language :: Python :: 3.11
Classifier: Programming Language :: Python :: 3.12
Classifier: Programming Language :: Python :: 3.13
Requires-Python: >=3.10
Requires-Dist: pytest>=8.4.1
Requires-Dist: result
Requires-Dist: ruff>=0.12.10
Requires-Dist: typing-extensions>=4.14.1
